README.md
setup.cfg
setup.py
superQuery/__init__.py
superQuery/magics.py
superQuery/superQuery.py
superQuery.egg-info/PKG-INFO
superQuery.egg-info/SOURCES.txt
superQuery.egg-info/dependency_links.txt
superQuery.egg-info/requires.txt
superQuery.egg-info/top_level.txt