Metadata-Version: 1.1
Name: superQuery
Version: 2.61
Summary: The Python interface to superQuery
Home-page: https://github.com/superquery/superPy
Author: Eben du Toit
Author-email: eben@superquery.io
License: MIT
Download-URL: https://github.com/superquery/superPy/archive/v2.6.tar.gz
Keywords: DATA,SUPERQUERY,BIGQUERY
Platform: UNKNOWN
Classifier: Development Status :: 3 - Alpha
Classifier: Intended Audience :: Developers
Classifier: Topic :: Software Development :: Build Tools
Classifier: License :: OSI Approved :: MIT License
Classifier: Programming Language :: Python :: 3
Classifier: Programming Language :: Python :: 3.4
Classifier: Programming Language :: Python :: 3.5
Classifier: Programming Language :: Python :: 3.6
Classifier: Programming Language :: Python :: 3.7
Classifier: Programming Language :: Python :: 3.8
